xapy/__init__.py
xapy/client.py
xapy/game.py
xapy/gamercard.py
xapy-0.0.1.dist-info/LICENSE
xapy-0.0.1.dist-info/METADATA
xapy-0.0.1.dist-info/WHEEL
xapy-0.0.1.dist-info/top_level.txt
xapy-0.0.1.dist-info/RECORD
